flagship_sdk/__init__.py
flagship_sdk/py.typed
flagship_sdk-1.0.0.dist-info/METADATA
flagship_sdk-1.0.0.dist-info/WHEEL
flagship_sdk-1.0.0.dist-info/licenses/LICENSE.txt
flagship_sdk-1.0.0.dist-info/RECORD
