Metadata-Version: 2.1
Name: flagship_sdk
Version: 1.0.0
Summary: Flagship SDK
Project-URL: Homepage, https://github.com/alexschimpf/flagship
Project-URL: Repository, https://github.com/alexschimpf/flagship
Author-email: Alex Schimpf <aschimpf1@gmaiil.com>
License: Copyright (c) 2012-2024 Scott Chacon and others
License-File: LICENSE.txt
Keywords: feature,feature flag,flag,flagship
Classifier: Environment :: Web Environment
Classifier: Operating System :: OS Independent
Classifier: Programming Language :: Python :: 3
Classifier: Programming Language :: Python :: 3.8
Classifier: Programming Language :: Python :: 3.9
Classifier: Programming Language :: Python :: 3.10
Classifier: Programming Language :: Python :: 3.11
Classifier: Programming Language :: Python :: 3.12
Classifier: Topic :: Internet
Classifier: Topic :: Software Development
Classifier: Topic :: Software Development :: Libraries
Classifier: Topic :: Software Development :: Libraries :: Python Modules
Classifier: Typing :: Typed
Requires-Python: >=3.8
Requires-Dist: requests==2.*
